{
  "name":"Project Phoenix",
  "version":"0.1",
  "type":"modded_standard",
  "provider":"technic",
  "enabled":true,
  "is_public": true,
  "minecraft":[
    "1.7.x"
  ],
  "resourcepacks":[
    "fanver",
    "invictus"
  ],
  "mods":[
    "aobd", 
    "appliedenergistics2", 
    "Baubles", 
    "BiblioCraft", 
    "AWWayofTime", 
    "Botania", 
    "BuildCraft", 
    "CarpentersBlocks", 
    "ChickenChunks", 
    "chisel", 
    "CoFHCore", 
    "compactmachines", 
    "Eln", 
    "Enchiridion", 
    "EnderIO", 
    "EnderStorage", 
    "enhancedportals", 
    "extracells", 
    "ExtraUtilities", 
    "Forestry", 
    "ForgeMultipart", 
    "Galacticraft", 
    "gregtech_addon", 
    "HardcoreQuesting", 
    "IguanaTweaksTConstruct", 
    "IC2", 
    "inventorytweaks", 
    "IronChest", 
    "JABBA", 
    "Mariculture", 
    "ImmibisMicroblocks", 
    "MineFactoryReloaded", 
    "Natura", 
    "NetherOres", 
    "NotEnoughItems", 
    "OpenBlocks", 
    "OpenEye", 
    "harvestcraft", 
    "PneumaticCraft", 
    "projectred", 
    "RandomThings", 
    "StevesCarts", 
    "ThermalExpansion", 
    "ThermalFoundation", 
    "TConstruct", 
    "TMechworks", 
    "TSteelworks" 
  ]
}
